neural_compressor/common/__init__.py
neural_compressor/common/base_config.py
neural_compressor/common/base_tuning.py
neural_compressor/common/tuning_param.py
neural_compressor/common/utils/__init__.py
neural_compressor/common/utils/constants.py
neural_compressor/common/utils/logger.py
neural_compressor/common/utils/save_load.py
neural_compressor/common/utils/utility.py
neural_compressor/onnxrt/__init__.py
neural_compressor/onnxrt/algorithms/__init__.py
neural_compressor/onnxrt/algorithms/layer_wise/__init__.py
neural_compressor/onnxrt/algorithms/layer_wise/core.py
neural_compressor/onnxrt/algorithms/smoother/__init__.py
neural_compressor/onnxrt/algorithms/smoother/calibrator.py
neural_compressor/onnxrt/algorithms/smoother/core.py
neural_compressor/onnxrt/algorithms/weight_only/__init__.py
neural_compressor/onnxrt/algorithms/weight_only/awq.py
neural_compressor/onnxrt/algorithms/weight_only/gptq.py
neural_compressor/onnxrt/algorithms/weight_only/rtn.py
neural_compressor/onnxrt/algorithms/weight_only/utility.py
neural_compressor/onnxrt/quantization/__init__.py
neural_compressor/onnxrt/quantization/algorithm_entry.py
neural_compressor/onnxrt/quantization/autotune.py
neural_compressor/onnxrt/quantization/calibrate.py
neural_compressor/onnxrt/quantization/config.py
neural_compressor/onnxrt/quantization/quantize.py
neural_compressor/onnxrt/utils/__init__.py
neural_compressor/onnxrt/utils/onnx_model.py
neural_compressor/onnxrt/utils/utility.py
neural_compressor_3x_ort-2.5.1.dist-info/LICENSE
neural_compressor_3x_ort-2.5.1.dist-info/METADATA
neural_compressor_3x_ort-2.5.1.dist-info/WHEEL
neural_compressor_3x_ort-2.5.1.dist-info/third-party-programs.txt
neural_compressor_3x_ort-2.5.1.dist-info/top_level.txt
neural_compressor_3x_ort-2.5.1.dist-info/RECORD
