Metadata-Version: 2.1
Name: neural_compressor_3x_ort
Version: 2.5.1
Summary: Repository of Intel® Neural Compressor
Home-page: https://github.com/intel/neural-compressor
Author: Intel AIPT Team
Author-email: feng.tian@intel.com, haihao.shen@intel.com, suyue.chen@intel.com
License: Apache 2.0
Keywords: quantization,auto-tuning,post-training static quantization,post-training dynamic quantization,quantization-aware training
Classifier: Intended Audience :: Science/Research
Classifier: Programming Language :: Python :: 3
Classifier: Topic :: Scientific/Engineering :: Artificial Intelligence
Classifier: License :: OSI Approved :: Apache Software License
Requires-Python: >=3.7.0
License-File: LICENSE
License-File: third-party-programs.txt
Requires-Dist: numpy
Requires-Dist: onnx
Requires-Dist: onnxruntime
Requires-Dist: onnxruntime-extensions
Requires-Dist: psutil
Requires-Dist: py-cpuinfo
Requires-Dist: pydantic
